pdsc/__init__.py
pdsc/client.py
pdsc/ingest.py
pdsc/localization.py
pdsc/metadata.py
pdsc/segment.py
pdsc/server.py
pdsc/table.py
pdsc/tools.py
pdsc/util.py
pdsc/version.py
pdsc/config/ctx_metadata.yaml
pdsc/config/hirise_edr_metadata.yaml
pdsc/config/hirise_rdr_metadata.yaml
pdsc/config/moc_metadata.yaml
pdsc/config/themis_ir_metadata.yaml
pdsc/config/themis_vis_metadata.yaml
pdsc-1.4.1.data/scripts/pdsc_ingest
pdsc-1.4.1.data/scripts/pdsc_server
pdsc-1.4.1.data/scripts/pdsc_util
pdsc-1.4.1.dist-info/LICENSE
pdsc-1.4.1.dist-info/METADATA
pdsc-1.4.1.dist-info/WHEEL
pdsc-1.4.1.dist-info/top_level.txt
pdsc-1.4.1.dist-info/RECORD
