Metadata-Version: 2.1
Name: pdsc
Version: 1.4.1
Summary: Planetary Data System Coincidences
Home-page: https://github.com/JPLMLIA/pdsc
Author: Gary Doran
Author-email: Gary.B.Doran.Jr@jpl.nasa.gov
License: BSD compatable (see the LICENSE file)
Platform: unix
Provides: pdsc
Requires-Python: >=2.7
Requires-Dist: numpy
Requires-Dist: scipy
Requires-Dist: scikit-learn
Requires-Dist: Polygon3
Requires-Dist: progressbar
Requires-Dist: PyYAML
Requires-Dist: geographiclib
Requires-Dist: CherryPy
Requires-Dist: requests
Requires-Dist: future
Provides-Extra: devel
Requires-Dist: pytest ; extra == 'devel'
Requires-Dist: pytest-cov ; extra == 'devel'
Requires-Dist: mock ; extra == 'devel'
Requires-Dist: sphinx ; extra == 'devel'
Requires-Dist: sphinx-rtd-theme ; extra == 'devel'
